{
  "clusters": {
    "P1": {
      "label": "影音輔導型",
      "count": 12,
      "values": [
        0.5556,
        0.7382,
        0.9155,
        0.5463,
        0.9802,
        0.4529
      ]
    },
    "P2": {
      "label": "彈性聽覺型",
      "count": 6,
      "values": [
        0.7393,
        0.4058,
        0.1921,
        0.1667,
        0.3492,
        0.1775
      ]
    },
    "P3": {
      "label": "平均使用型",
      "count": 2004,
      "values": [
        0.1754,
        0.3593,
        0.4755,
        0.1442,
        0.3829,
        0.3587
      ]
    },
    "P4": {
      "label": "題庫刷題型",
      "count": 666,
      "values": [
        0.1018,
        0.2782,
        0.3847,
        0.1069,
        0.2488,
        0.3576
      ]
    },
    "P5": {
      "label": "被動低參與型",
      "count": 9,
      "values": [
        0.0,
        0.0,
        0.0571,
        0.0,
        0.0,
        0.2053
      ]
    }
  },
  "pass_vs_fail": {
    "pass": {
      "label": "及格（≥60）",
      "count": 1184,
      "values": [
        0.1647,
        0.3406,
        0.4592,
        0.2184,
        0.341,
        0.35
      ]
    },
    "fail": {
      "label": "不及格（<60）",
      "count": 1513,
      "values": [
        0.1556,
        0.3393,
        0.4481,
        0.0722,
        0.3589,
        0.3641
      ]
    }
  },
  "meta": {
    "schema_version": "2.0",
    "semester": "1141",
    "semesters": [
      "1111",
      "1112",
      "1121",
      "1122",
      "1131",
      "1132",
      "1141",
      "1142"
    ],
    "semester_range": "111(1)-114(2)",
    "semester_range_label": "111(1)-114(2)",
    "generated_at": "2026-05-07T14:11:51",
    "dimensions": [
      "AUD",
      "VID",
      "TXT",
      "SUP",
      "TUT",
      "QUZ"
    ],
    "cluster_labels": {
      "P1": "影音輔導型",
      "P2": "彈性聽覺型",
      "P3": "平均使用型",
      "P4": "題庫刷題型",
      "P5": "被動低參與型"
    },
    "student_count": 2697
  }
}